frpython/__init__.py
frpython/booleen.py
frpython/chaines.py
frpython/decimaux.py
frpython/entiers.py
frpython/erreurs.py
frpython/fonctions.py
frpython-1.4.dist-info/LICENSE
frpython-1.4.dist-info/METADATA
frpython-1.4.dist-info/WHEEL
frpython-1.4.dist-info/top_level.txt
frpython-1.4.dist-info/RECORD
