Metadata-Version: 2.1
Name: frpython
Version: 1.4
Summary: Tentative de traduction de python en francais
Home-page: https://github.com/Gatien-Oudoire/python-fr
Author: Gatien Oudoire
License: UNKNOWN
Download-URL: https://pypi.org/project/frpython
Platform: UNKNOWN
Classifier: Programming Language :: Python :: 3
Classifier: Operating System :: OS Independent
License-File: LICENSE
